{"id":81846,"title":"43 | 实战MNIST CNN网络","content":"<h2>课件及源码下载地址：</h2><p><a href=\"https://gitee.com/geektime-geekbang/tensorflow-101/tree/master/beginners\">https://gitee.com/geektime-geekbang/tensorflow-101/tree/master/beginners</a></p>","comments":[{"had_liked":false,"id":68181,"user_name":"凌","can_delete":false,"product_type":"c3","uid":1257995,"ip_address":"","ucode":"41369B360C794F","user_header":"https://static001.geekbang.org/account/avatar/00/13/32/0b/81ae214b.jpg","comment_is_top":false,"comment_ctime":1550454555,"is_pvip":false,"replies":[{"id":26656,"content":"最后一章会简单介绍","user_name":"作者回复","user_name_real":"彭靖田","uid":1067283,"ctime":1551848475,"ip_address":"","comment_id":68181,"utype":1}],"discussion_count":1,"race_medal":0,"score":2,"product_id":100023001,"comment_content":"希望后面能讲到kubeflow相关的。关于系统流程化数据处理，存储，训练，模型管理服务发布。","like_count":1,"discussions":[{"author":{"id":1067283,"avatar":"https://static001.geekbang.org/account/avatar/00/10/49/13/51b1fe81.jpg","nickname":"彭靖田","note":"","ucode":"D3F1C281F38390","race_medal":0,"user_type":2,"is_pvip":false},"reply_author":{"id":0,"avatar":"","nickname":"","note":"","ucode":"","race_medal":0,"user_type":1,"is_pvip":false},"discussion":{"id":439551,"discussion_content":"最后一章会简单介绍","likes_number":0,"is_delete":false,"is_hidden":false,"ctime":1551848475,"is_liked":false,"can_delete":false,"is_complain":false,"is_top":true,"parent_id":0,"ip_address":"","group_id":0},"score":2,"extra":"{\"reply\":true,\"user_type\":2}","child_discussion_number":0,"child_discussions":[]}]},{"had_liked":false,"id":67661,"user_name":"victoriest","can_delete":false,"product_type":"c3","uid":1023394,"ip_address":"","ucode":"7B4232B0FB88F6","user_header":"https://static001.geekbang.org/account/avatar/00/0f/9d/a2/d8a708cc.jpg","comment_is_top":false,"comment_ctime":1550219562,"is_pvip":false,"replies":[{"id":26657,"content":"嗯，这个展开就比较大了，将来有机会再分享吧。","user_name":"作者回复","user_name_real":"彭靖田","uid":1067283,"ctime":1551848605,"ip_address":"","comment_id":67661,"utype":1}],"discussion_count":1,"race_medal":0,"score":2,"product_id":100023001,"comment_content":"建议讲解一下keras结合tensorboard","like_count":1,"discussions":[{"author":{"id":1067283,"avatar":"https://static001.geekbang.org/account/avatar/00/10/49/13/51b1fe81.jpg","nickname":"彭靖田","note":"","ucode":"D3F1C281F38390","race_medal":0,"user_type":2,"is_pvip":false},"reply_author":{"id":0,"avatar":"","nickname":"","note":"","ucode":"","race_medal":0,"user_type":1,"is_pvip":false},"discussion":{"id":439311,"discussion_content":"嗯，这个展开就比较大了，将来有机会再分享吧。","likes_number":0,"is_delete":false,"is_hidden":false,"ctime":1551848605,"is_liked":false,"can_delete":false,"is_complain":false,"is_top":true,"parent_id":0,"ip_address":"","group_id":0},"score":2,"extra":"{\"reply\":true,\"user_type\":2}","child_discussion_number":0,"child_discussions":[]}]},{"had_liked":false,"id":77120,"user_name":"雁声惊寒","can_delete":false,"product_type":"c3","uid":1067218,"ip_address":"","ucode":"A5FF9FDA052F31","user_header":"https://static001.geekbang.org/account/avatar/00/10/48/d2/15fccccc.jpg","comment_is_top":false,"comment_ctime":1552839045,"is_pvip":false,"replies":[{"id":36076,"content":"经验值。","user_name":"作者回复","user_name_real":"彭靖田","uid":1067283,"ctime":1559535360,"ip_address":"","comment_id":77120,"utype":1}],"discussion_count":2,"race_medal":0,"score":2,"product_id":100023001,"comment_content":"请问要训练的模型参数个数是怎么求出来的，特别是第二层卷积层的参数","like_count":0,"discussions":[{"author":{"id":1067283,"avatar":"https://static001.geekbang.org/account/avatar/00/10/49/13/51b1fe81.jpg","nickname":"彭靖田","note":"","ucode":"D3F1C281F38390","race_medal":0,"user_type":2,"is_pvip":false},"reply_author":{"id":0,"avatar":"","nickname":"","note":"","ucode":"","race_medal":0,"user_type":1,"is_pvip":false},"discussion":{"id":443586,"discussion_content":"经验值。","likes_number":0,"is_delete":false,"is_hidden":false,"ctime":1559535360,"is_liked":false,"can_delete":false,"is_complain":false,"is_top":true,"parent_id":0,"ip_address":"","group_id":0},"score":2,"extra":"{\"reply\":true,\"user_type\":2}","child_discussion_number":0,"child_discussions":[]},{"author":{"id":2129421,"avatar":"https://static001.geekbang.org/account/avatar/00/20/7e/0d/5ec4c807.jpg","nickname":"不熬夜","note":"","ucode":"C51790211B4347","race_medal":0,"user_type":1,"is_pvip":false},"reply_author":{"id":0,"avatar":"","nickname":"","note":"","ucode":"","race_medal":0,"user_type":1,"is_pvip":false},"discussion":{"id":307818,"discussion_content":"您好，想问一下第二个64通道的卷积层如何和前一个32通道的卷积层结果卷积的，最后输出结果总觉的是24*24*（32*64）","likes_number":0,"is_delete":false,"is_hidden":false,"ctime":1600765782,"is_liked":false,"can_delete":false,"is_complain":false,"is_top":false,"parent_id":0,"ip_address":"","group_id":0},"score":2,"extra":"","child_discussion_number":0,"child_discussions":[]}]},{"had_liked":false,"id":70593,"user_name":"松烽","can_delete":false,"product_type":"c3","uid":1072474,"ip_address":"","ucode":"D850DBBBD3DAF0","user_header":"https://static001.geekbang.org/account/avatar/00/10/5d/5a/44858499.jpg","comment_is_top":false,"comment_ctime":1551144725,"is_pvip":false,"replies":[{"id":26645,"content":"想要了解底层的原理，《深入理解TensorFlow》书里其实有讲解。如果我们视频课程做一个偏底层的，可能对新人不太友好。Keras 的易用性和简洁性，对于入门还是不错的。","user_name":"作者回复","user_name_real":"彭靖田","uid":1067283,"ctime":1551847898,"ip_address":"","comment_id":70593,"utype":1}],"discussion_count":1,"race_medal":0,"score":2,"product_id":100023001,"comment_content":"通过各种查资料，各种的学习，发现keras不太能理解tensorflow的一些运行机制，希望老师多讲一些tensorflow低阶的例子","like_count":0,"discussions":[{"author":{"id":1067283,"avatar":"https://static001.geekbang.org/account/avatar/00/10/49/13/51b1fe81.jpg","nickname":"彭靖田","note":"","ucode":"D3F1C281F38390","race_medal":0,"user_type":2,"is_pvip":false},"reply_author":{"id":0,"avatar":"","nickname":"","note":"","ucode":"","race_medal":0,"user_type":1,"is_pvip":false},"discussion":{"id":440715,"discussion_content":"想要了解底层的原理，《深入理解TensorFlow》书里其实有讲解。如果我们视频课程做一个偏底层的，可能对新人不太友好。Keras 的易用性和简洁性，对于入门还是不错的。","likes_number":0,"is_delete":false,"is_hidden":false,"ctime":1551847898,"is_liked":false,"can_delete":false,"is_complain":false,"is_top":true,"parent_id":0,"ip_address":"","group_id":0},"score":2,"extra":"{\"reply\":true,\"user_type\":2}","child_discussion_number":0,"child_discussions":[]}]},{"had_liked":false,"id":67943,"user_name":"。。。","can_delete":false,"product_type":"c3","uid":1369467,"ip_address":"","ucode":"B0096EDE3C398B","user_header":"https://static001.geekbang.org/account/avatar/00/14/e5/7b/3fb039bf.jpg","comment_is_top":false,"comment_ctime":1550329828,"is_pvip":false,"replies":null,"discussion_count":0,"race_medal":0,"score":2,"product_id":100023001,"comment_content":"老师您好，能不能给予一些关于电脑配置的建议，比如GPU和CPU等。目前我自己的笔记本还是在使用CPU训练，速度很慢，所以想入手一台新的电脑。先谢谢老师您了","like_count":3},{"had_liked":false,"id":68553,"user_name":"姜昆","can_delete":false,"product_type":"c3","uid":1369770,"ip_address":"","ucode":"2B14C5503DFC63","user_header":"https://static001.geekbang.org/account/avatar/00/14/e6/aa/7c0fc559.jpg","comment_is_top":false,"comment_ctime":1550542995,"is_pvip":false,"replies":null,"discussion_count":0,"race_medal":0,"score":2,"product_id":100023001,"comment_content":"不设置滑动窗口，那么默认应该是1吧，你讲的0应该是如何理解？？？\n\n","like_count":1},{"had_liked":false,"id":380756,"user_name":"BK","can_delete":false,"product_type":"c3","uid":3635181,"ip_address":"福建","ucode":"9AA61DD2B93C8F","user_header":"https://static001.geekbang.org/account/avatar/00/37/77/ed/77cd33ee.jpg","comment_is_top":false,"comment_ctime":1694092934,"is_pvip":false,"replies":null,"discussion_count":0,"race_medal":0,"score":2,"product_id":100023001,"comment_content":"可以把错误的图片显示出来吗","like_count":0},{"had_liked":false,"id":380755,"user_name":"BK","can_delete":false,"product_type":"c3","uid":3635181,"ip_address":"福建","ucode":"9AA61DD2B93C8F","user_header":"https://static001.geekbang.org/account/avatar/00/37/77/ed/77cd33ee.jpg","comment_is_top":false,"comment_ctime":1694092629,"is_pvip":false,"replies":null,"discussion_count":0,"race_medal":0,"score":2,"product_id":100023001,"comment_content":"为什么使用3*3的卷积核?而不是4*4","like_count":0},{"had_liked":false,"id":380754,"user_name":"BK","can_delete":false,"product_type":"c3","uid":3635181,"ip_address":"福建","ucode":"9AA61DD2B93C8F","user_header":"https://static001.geekbang.org/account/avatar/00/37/77/ed/77cd33ee.jpg","comment_is_top":false,"comment_ctime":1694092099,"is_pvip":false,"replies":null,"discussion_count":0,"race_medal":0,"score":2,"product_id":100023001,"comment_content":"不是讲tensorflow吗,怎么又讲keras","like_count":0},{"had_liked":false,"id":249709,"user_name":"不熬夜","can_delete":false,"product_type":"c3","uid":2129421,"ip_address":"","ucode":"C51790211B4347","user_header":"https://static001.geekbang.org/account/avatar/00/20/7e/0d/5ec4c807.jpg","comment_is_top":false,"comment_ctime":1600766019,"is_pvip":false,"replies":null,"discussion_count":0,"race_medal":0,"score":2,"product_id":100023001,"comment_content":"老师您好，刚开始学习深度学习，有两个问题想要请教\n1、想问一下第二个64通道的卷积层如何和前一个32通道的卷积层结果卷积的，最后输出结果的shape为什么不是24*24*（32*64）\n2、dropout层既然丢掉了一部分神经元，为什么shape和前一层的shape相同?","like_count":0}]}