{"id":84661,"title":"52 | 第七部分内容介绍","content":"<h2>课件及源码下载地址：</h2><p><a href=\"https://gitee.com/geektime-geekbang/tensorflow-101/tree/master/beginners\">https://gitee.com/geektime-geekbang/tensorflow-101/tree/master/beginners</a></p>","comments":[{"had_liked":false,"id":73820,"user_name":"王健","can_delete":false,"product_type":"c3","uid":1146674,"ip_address":"","ucode":"8E999AB61E62EA","user_header":"https://static001.geekbang.org/account/avatar/00/11/7f/32/422429f9.jpg","comment_is_top":false,"comment_ctime":1552010146,"is_pvip":false,"replies":[{"id":26953,"content":"已更新，请注意查看","user_name":"作者回复","user_name_real":"彭靖田","uid":1067283,"ctime":1552014226,"ip_address":"","comment_id":73820,"utype":1}],"discussion_count":1,"race_medal":0,"score":2,"product_id":100023001,"comment_content":"老师 , 尽快把人脸识别实战的这个最后一个项目放出来啊 , 老师我考研复试要用您的项目啊,  麻烦了啊","like_count":2,"discussions":[{"author":{"id":1067283,"avatar":"https://static001.geekbang.org/account/avatar/00/10/49/13/51b1fe81.jpg","nickname":"彭靖田","note":"","ucode":"D3F1C281F38390","race_medal":0,"user_type":2,"is_pvip":false},"reply_author":{"id":0,"avatar":"","nickname":"","note":"","ucode":"","race_medal":0,"user_type":1,"is_pvip":false},"discussion":{"id":442294,"discussion_content":"已更新，请注意查看","likes_number":0,"is_delete":false,"is_hidden":false,"ctime":1552014226,"is_liked":false,"can_delete":false,"is_complain":false,"is_top":true,"parent_id":0,"ip_address":"","group_id":0},"score":2,"extra":"{\"reply\":true,\"user_type\":2}","child_discussion_number":0,"child_discussions":[]}]},{"had_liked":false,"id":94790,"user_name":"Mumu_","can_delete":false,"product_type":"c3","uid":1063376,"ip_address":"","ucode":"146772C8D3D2B8","user_header":"https://static001.geekbang.org/account/avatar/00/10/39/d0/62278002.jpg","comment_is_top":false,"comment_ctime":1557898378,"is_pvip":false,"replies":null,"discussion_count":0,"race_medal":0,"score":2,"product_id":100023001,"comment_content":"考研复试的太可爱了! 老师很给力 哈哈","like_count":1},{"had_liked":false,"id":78613,"user_name":"守护露","can_delete":false,"product_type":"c3","uid":1156204,"ip_address":"","ucode":"C7FB69841CFC80","user_header":"https://static001.geekbang.org/account/avatar/00/11/a4/6c/32ec4991.jpg","comment_is_top":false,"comment_ctime":1553183268,"is_pvip":false,"replies":null,"discussion_count":0,"race_medal":0,"score":2,"product_id":100023001,"comment_content":"haha考研复试用上人脸识别就太惨了吧，不过能理解人脸识别也是好的","like_count":1}]}