{"id":682356,"title":"07｜为了解决问题的研讨会，要怎么开？","content":"","comments":[{"had_liked":false,"id":379352,"user_name":"进化菌","can_delete":false,"product_type":"c3","uid":1276861,"ip_address":"广东","ucode":"B30A5F78BB4171","user_header":"https://static001.geekbang.org/account/avatar/00/13/7b/bd/ccb37425.jpg","comment_is_top":false,"comment_ctime":1691805943,"is_pvip":true,"replies":null,"discussion_count":0,"race_medal":4,"score":2,"product_id":100611101,"comment_content":"研讨会，复盘应该也是一种，找到真正的原因和下次要注意的地方。\n\n我们开发真正出问题的时候，我们都习惯火急火燎的解决问题，可能都只是快速解决表面问题，这是快问题。\n课程里说的，大概是慢问题，可以按照流程，识别和描述问题，分析拆解问题，制定方案，形成结果选择决策。决策，需要把方案、时间、有效性、可行性、成本、风险等都注明。接下来，就是制定计划。","like_count":0}]}