{"id":299068,"title":"期末测试｜有关动态规划，你掌握了多少呢？","content":"<p>你好，我是卢誉声。</p><p>《动态规划面试宝典》这个专栏到今天就结课了，很感谢大家的支持，也非常开心能与各位交流技术。为认真学习的你点赞！</p><p>为了让你更好地检测自己的学习成果，我特意做了一套期末测试题。题目共有20道，其中单选3道、多选17道，满分100分，快来挑战一下吧！</p><p><a href=\"http://time.geekbang.org/quiz/intro?act_id=227&exam_id=745\"><img src=\"https://static001.geekbang.org/resource/image/28/a4/28d1be62669b4f3cc01c36466bf811a4.png?wh=1142*201\" alt=\"\"></a></p><!-- [[[read_end]]] -->","comments":[{"had_liked":false,"id":259490,"user_name":"Jacob.C","can_delete":false,"product_type":"c1","uid":1070253,"ip_address":"","ucode":"034998E7A7CCD1","user_header":"https://static001.geekbang.org/account/avatar/00/10/54/ad/6ee2b7cb.jpg","comment_is_top":false,"comment_ctime":1604735473,"is_pvip":false,"replies":[{"id":"94522","content":"是的，已修正，感谢反馈！18题为多选题。","user_name":"编辑回复","user_name_real":"王冬青","uid":"1356014","ctime":1604997843,"ip_address":"","comment_id":259490,"utype":2}],"discussion_count":1,"race_medal":0,"score":"5899702769","product_id":100060501,"comment_content":"路径规划障碍那题，解析说障碍不影响空间复杂度和时间复杂度，但是题目是单选题。","like_count":2,"discussions":[{"author":{"id":1356014,"avatar":"https://static001.geekbang.org/account/avatar/00/14/b0/ee/d0871efd.jpg","nickname":"冬青","note":"","ucode":"14576781B499FB","race_medal":0,"user_type":8,"is_pvip":false},"reply_author":{"id":0,"avatar":"","nickname":"","note":"","ucode":"","race_medal":0,"user_type":1,"is_pvip":false},"discussion":{"id":508944,"discussion_content":"是的，已修正，感谢反馈！18题为多选题。","likes_number":0,"is_delete":false,"is_hidden":false,"ctime":1604997843,"is_liked":false,"can_delete":false,"is_complain":false,"is_top":true,"parent_id":0,"ip_address":""},"score":2,"extra":"{\"reply\":true,\"user_type\":4}","child_discussion_number":0,"child_discussions":[]}]}]}