{"id":309762,"title":"结课问卷获奖用户名单","content":"<p>你好！十分感谢你的参与，现在我们来公布一下获奖用户名单。</p><p>在这里，我首先要感谢各位同学给我们的反馈，你们的声音可以促使我们精益求精。在这些反馈中，我们看到了很多非常有价值的信息，也收获了很多的支持与肯定。在此，我们精选出了反馈最为具体、丰富，最有实际价值的 5 位用户，送出奖品。中奖名单如下：</p><p><img src=\"https://static001.geekbang.org/resource/image/1f/12/1f3edf1d0258b950735ceed25bcb0512.jpg?wh=4437*2248\" alt=\"\"></p><p>恭喜这 5 位同学，也再次感谢所有参与调研的同学。希望大家今后还能多多支持，给予宝贵意见。</p><!-- [[[read_end]]] -->","comments":[{"had_liked":false,"id":261968,"user_name":"冬青","can_delete":false,"product_type":"c1","uid":1356014,"ip_address":"","ucode":"14576781B499FB","user_header":"https://static001.geekbang.org/account/avatar/00/14/b0/ee/d0871efd.jpg","comment_is_top":true,"comment_ctime":1605592840,"is_pvip":false,"discussion_count":0,"race_medal":0,"score":"9.2233720384603996e+18","product_id":100060501,"comment_content":"中奖用户可添加微信15600218688领取奖品！","like_count":1}]}