{"id":228341,"title":"60 | Transformer：如何通过Transformer榨取重要变量？","content":"<p><strong>课件和Demo地址</strong><br>\n<a href=\"https://gitee.com/geektime-geekbang/NLP\">https://gitee.com/geektime-geekbang/NLP</a></p>","comments":[{"had_liked":false,"id":239268,"user_name":"jayjay","can_delete":false,"product_type":"c3","uid":1883251,"ip_address":"","ucode":"5E05BAD9D18ADC","user_header":"http://thirdwx.qlogo.cn/mmopen/vi_32/DYAIOgq83erl1w8oy6XV3J8FczdVBp0Xj2aibqFyqa1v7kHT2LC7aEn0CbKNWByHMM8e8tuHOrW7e6uX6iaCVZHw/132","comment_is_top":false,"comment_ctime":1596470919,"is_pvip":false,"replies":null,"discussion_count":0,"race_medal":0,"score":2,"product_id":100046401,"comment_content":"所以，到底是「如何通过Transformer榨取重要变量？」这里的目的是要干吗","like_count":1},{"had_liked":false,"id":338173,"user_name":"Anti-Gravity","can_delete":false,"product_type":"c3","uid":2000797,"ip_address":"","ucode":"D4381C64BB68E1","user_header":"https://static001.geekbang.org/account/avatar/00/1e/87/9d/62f3eff3.jpg","comment_is_top":false,"comment_ctime":1647334945,"is_pvip":false,"replies":null,"discussion_count":0,"race_medal":0,"score":2,"product_id":100046401,"comment_content":"您关于Multihead的解释大意是，为了获得不同的三个QKV矩阵。但事实似乎并非如此。因为QKV本是通过三个不同的权重矩阵乘以输入X后得到的。更为可能的解释似乎是，Attention机制通过Multihead可以获得不同子空间的特征，因为对不同head获取QKV时的三个矩阵都是不同的。好处在于，例如一个词用64维表示，分为8个head时，每个8维子空间都有着不同的含义，因此该用不同的权重提取出相应的QKV，而不是粗暴地用一个权重阵直接对64维空间提取出一组QKV。","like_count":0},{"had_liked":false,"id":279044,"user_name":"Eric","can_delete":false,"product_type":"c3","uid":1140494,"ip_address":"","ucode":"8FFC6764ED327B","user_header":"https://static001.geekbang.org/account/avatar/00/11/67/0e/2a51a2df.jpg","comment_is_top":false,"comment_ctime":1613567058,"is_pvip":false,"replies":null,"discussion_count":0,"race_medal":0,"score":2,"product_id":100046401,"comment_content":"1. 全连接层 加的很深的时候 为什么一方面可能过拟合 一方面可能欠拟合呢?\n2.多层LSTM 为什么很难收敛? Residual Connetcion?","like_count":0},{"had_liked":false,"id":256757,"user_name":"Eric","can_delete":false,"product_type":"c3","uid":1140494,"ip_address":"","ucode":"8FFC6764ED327B","user_header":"https://static001.geekbang.org/account/avatar/00/11/67/0e/2a51a2df.jpg","comment_is_top":false,"comment_ctime":1603723100,"is_pvip":false,"replies":null,"discussion_count":0,"race_medal":0,"score":2,"product_id":100046401,"comment_content":"误差是指样本误差吗，比如有噪音或者数据太少了等等","like_count":0}]}