{"id":776335,"title":"11｜RAG类应用案例解析：怎么做一个“民法典助手”？","content":"<p>民法典全文PDF下载链接：<a href=\"https://www.yueyang.gov.cn/uploadfiles/202101/20210105110045320.pdf\">https://www.yueyang.gov.cn/uploadfiles/202101/20210105110045320.pdf</a></p>","comments":[{"had_liked":false,"id":391103,"user_name":"Geek_6a030c","can_delete":false,"product_type":"c3","uid":3899959,"ip_address":"四川","ucode":"3CADC0CABB221B","user_header":"","comment_is_top":false,"comment_ctime":1717329630,"is_pvip":false,"replies":null,"discussion_count":0,"race_medal":0,"score":2,"product_id":100768001,"comment_content":"通过浅显易懂的实例讲解，让毫无基础的人都能听懂，非常非常好的课程，值得购买！","like_count":1}]}