{"id":812833,"title":"06｜基本使用实操：代码提示补全","content":"","comments":[{"had_liked":false,"id":394760,"user_name":"Geek_79e23f","can_delete":false,"product_type":"c3","uid":2876133,"ip_address":"上海","ucode":"3230707F80601C","user_header":"https://thirdwx.qlogo.cn/mmopen/vi_32/8t1ibxveiaNUeQF2PlZaQMC5Wtjdhg43NiaEtgn0Mdf3bAlxlqicyLMZwlAlS0WJEdk6Bm0fR07ZWJtmqqfgWFn3MNhp2Q2mgPz5jVib5h2qONu8/132","comment_is_top":false,"comment_ctime":1728140890,"is_pvip":false,"replies":[{"id":143443,"content":"大家对课程有什么建议和想了解的，也可以学习后再下面留言","user_name":"作者回复","user_name_real":"编辑","uid":2876133,"ctime":1729144759,"ip_address":"上海","comment_id":394760,"utype":1}],"discussion_count":1,"race_medal":0,"score":2,"product_id":100821001,"comment_content":"https:&#47;&#47;github.com&#47;laziobird&#47;CodeLLMEval&#47;blob&#47;main&#47;lesson&#47;%E6%9E%81%E5%AE%A2%E6%97%B6%E9%97%B4%E8%AF%BE%E4%BB%B6%E6%A1%88%E4%BE%8B%E5%86%85%E5%AE%B9.md#8%E4%BB%A3%E7%A0%81%E8%A1%A5%E5%85%A8-%E9%A1%B9%E7%9B%AE-p32","like_count":0,"discussions":[{"author":{"id":2876133,"avatar":"https://thirdwx.qlogo.cn/mmopen/vi_32/8t1ibxveiaNUeQF2PlZaQMC5Wtjdhg43NiaEtgn0Mdf3bAlxlqicyLMZwlAlS0WJEdk6Bm0fR07ZWJtmqqfgWFn3MNhp2Q2mgPz5jVib5h2qONu8/132","nickname":"Geek_79e23f","note":"","ucode":"3230707F80601C","race_medal":0,"user_type":2,"is_pvip":false},"reply_author":{"id":0,"avatar":"","nickname":"","note":"","ucode":"","race_medal":0,"user_type":1,"is_pvip":false},"discussion":{"id":652556,"discussion_content":"大家对课程有什么建议和想了解的，也可以学习后再下面留言","likes_number":0,"is_delete":false,"is_hidden":false,"ctime":1729144759,"is_liked":false,"can_delete":false,"is_complain":false,"is_top":true,"parent_id":0,"ip_address":"上海","group_id":0},"score":2,"extra":"{\"reply\":true,\"user_type\":2,\"source\":0}","child_discussion_number":0,"child_discussions":[]}]}]}