{"id":12041,"title":"18 | 神奇的符号 : Kotlin 的反引号","content":"<h1>源代码及 PDF 课件地址：</h1><p><strong><a href=\"https://gitee.com/geektime-geekbang/KotlinPrimer\">https://gitee.com/geektime-geekbang/KotlinPrimer</a></strong></p>","comments":[{"had_liked":false,"id":98505,"user_name":"遥远的救世主","can_delete":false,"product_type":"c3","uid":1181334,"ip_address":"","ucode":"4CC436479CAA21","user_header":"https://static001.geekbang.org/account/avatar/00/12/06/96/4273bb09.jpg","comment_is_top":false,"comment_ctime":1559013740,"is_pvip":false,"replies":null,"discussion_count":0,"race_medal":0,"score":2,"product_id":100009801,"comment_content":"之前什么还不懂的情况下还把别人的==画蛇添足的改成equals，内心还会窃喜，以为代码规范呢，孰不知贻笑于大方之家矣，看来一定要多读书！！！","like_count":0}]}