{"id":12053,"title":"30 | suspend : 知其然知其所以然","content":"<h1>源代码及 PDF 课件地址：</h1><p><strong><a href=\"https://gitee.com/geektime-geekbang/KotlinPrimer\">https://gitee.com/geektime-geekbang/KotlinPrimer</a></strong></p>","comments":[{"had_liked":false,"id":41515,"user_name":"刘建","can_delete":false,"product_type":"c3","uid":1184348,"ip_address":"","ucode":"8FAA03E146B16F","user_header":"http://thirdwx.qlogo.cn/mmopen/vi_32/RRyBNDRiaQ1rfDf2es0Gw8kWMUtFrITmIIfPBjYUtKNcOVBgO85AsdGlibPdoicBibsIoiatOM2QKKzbjD51kLKPObA/132","comment_is_top":false,"comment_ctime":1542797395,"is_pvip":false,"replies":[{"id":15178,"content":"用于标识一个函数是协程函数，因为suspend函数在编译以后会额外的添加一个参数","user_name":"作者回复","user_name_real":"kymjs张涛","uid":1009146,"ctime":1542962220,"ip_address":"","comment_id":41515,"utype":1}],"discussion_count":1,"race_medal":0,"score":2,"product_id":100009801,"comment_content":"suspend关键字的作用是什么呢","like_count":2,"discussions":[{"author":{"id":1009146,"avatar":"https://static001.geekbang.org/account/avatar/00/0f/65/fa/2b4d2f26.jpg","nickname":"kymjs张涛","note":"","ucode":"EFE7AF4C0D4FE8","race_medal":0,"user_type":2,"is_pvip":false},"reply_author":{"id":0,"avatar":"","nickname":"","note":"","ucode":"","race_medal":0,"user_type":1,"is_pvip":false},"discussion":{"id":429829,"discussion_content":"用于标识一个函数是协程函数，因为suspend函数在编译以后会额外的添加一个参数","likes_number":0,"is_delete":false,"is_hidden":false,"ctime":1542962220,"is_liked":false,"can_delete":false,"is_complain":false,"is_top":true,"parent_id":0,"ip_address":"","group_id":0},"score":2,"extra":"{\"reply\":true,\"user_type\":2}","child_discussion_number":0,"child_discussions":[]}]},{"had_liked":false,"id":24197,"user_name":"光着脚丫子飙五环","can_delete":false,"product_type":"c3","uid":1180243,"ip_address":"","ucode":"FC4681883A895F","user_header":"https://static001.geekbang.org/account/avatar/00/12/02/53/ed2600ae.jpg","comment_is_top":false,"comment_ctime":1536840125,"is_pvip":false,"replies":[{"id":10510,"content":"这两个函数并没有什么联系，join是所有协程都有的方法，作用类似于线程的join，await是deferred的一个方法，类似回调，用于返回deferrd的结果","user_name":"作者回复","user_name_real":"kymjs张涛","uid":1009146,"ctime":1538307202,"ip_address":"","comment_id":24197,"utype":1}],"discussion_count":1,"race_medal":0,"score":2,"product_id":100009801,"comment_content":"麻烦问下:launch和async说白了都是协程启动器，那join方法和await方法的区别在哪呢","like_count":1,"discussions":[{"author":{"id":1009146,"avatar":"https://static001.geekbang.org/account/avatar/00/0f/65/fa/2b4d2f26.jpg","nickname":"kymjs张涛","note":"","ucode":"EFE7AF4C0D4FE8","race_medal":0,"user_type":2,"is_pvip":false},"reply_author":{"id":0,"avatar":"","nickname":"","note":"","ucode":"","race_medal":0,"user_type":1,"is_pvip":false},"discussion":{"id":423876,"discussion_content":"这两个函数并没有什么联系，join是所有协程都有的方法，作用类似于线程的join，await是deferred的一个方法，类似回调，用于返回deferrd的结果","likes_number":0,"is_delete":false,"is_hidden":false,"ctime":1538307202,"is_liked":false,"can_delete":false,"is_complain":false,"is_top":true,"parent_id":0,"ip_address":"","group_id":0},"score":2,"extra":"{\"reply\":true,\"user_type\":2}","child_discussion_number":0,"child_discussions":[]}]}]}