{"id":76552,"title":"08 | TensorFlow的发展现状","content":"<h2>课件及源码下载地址：</h2><p><a href=\"https://gitee.com/geektime-geekbang/tensorflow-101/tree/master/beginners\">https://gitee.com/geektime-geekbang/tensorflow-101/tree/master/beginners</a></p>","comments":[{"had_liked":false,"id":67078,"user_name":"奕","can_delete":false,"product_type":"c3","uid":1005391,"ip_address":"","ucode":"73CEA468CE70C3","user_header":"https://static001.geekbang.org/account/avatar/00/0f/57/4f/6fb51ff1.jpg","comment_is_top":false,"comment_ctime":1550068336,"is_pvip":false,"replies":null,"discussion_count":0,"race_medal":0,"score":2,"product_id":100023001,"comment_content":"使用 stars:&gt;100000 在github上搜索可以查看tensorflow的排名，目前排名是第5","like_count":9},{"had_liked":false,"id":58401,"user_name":"icejoywoo","can_delete":false,"product_type":"c3","uid":1019222,"ip_address":"","ucode":"E68C8B54D07EC3","user_header":"https://static001.geekbang.org/account/avatar/00/0f/8d/56/2a04dd88.jpg","comment_is_top":false,"comment_ctime":1547054636,"is_pvip":false,"replies":null,"discussion_count":0,"race_medal":0,"score":2,"product_id":100023001,"comment_content":"第一个r是rust","like_count":4},{"had_liked":false,"id":390764,"user_name":"神经蛙","can_delete":false,"product_type":"c3","uid":3892313,"ip_address":"天津","ucode":"581D92DF36A1A2","user_header":"https://static001.geekbang.org/account/avatar/00/3b/64/59/1a7f838c.jpg","comment_is_top":false,"comment_ctime":1716200407,"is_pvip":false,"replies":null,"discussion_count":0,"race_medal":0,"score":2,"product_id":100023001,"comment_content":"这是18年的课么。。我这都24年了。。","like_count":0},{"had_liked":false,"id":390763,"user_name":"神经蛙","can_delete":false,"product_type":"c3","uid":3892313,"ip_address":"天津","ucode":"581D92DF36A1A2","user_header":"https://static001.geekbang.org/account/avatar/00/3b/64/59/1a7f838c.jpg","comment_is_top":false,"comment_ctime":1716200316,"is_pvip":false,"replies":null,"discussion_count":0,"race_medal":0,"score":2,"product_id":100023001,"comment_content":"巴西还挺多，","like_count":0}]}