{"id":778582,"title":"14｜Stable Diffusion WebUI安装与配置","content":"<ol>\n<li>算力选择 PAI-DSW：<a href=\"https://www.aliyun.com/activity/bigdata/pai/dsw\">https://www.aliyun.com/activity/bigdata/pai/dsw</a></li>\n<li>官方仓库：<a href=\"https://github.com/AUTOMATIC1111/stable-diffusion-webui/releases/tag/v1.8.0\">https://github.com/AUTOMATIC1111/stable-diffusion-webui/releases/tag/v1.8.0</a></li>\n<li>秋叶启动器教程：<a href=\"https://www.bilibili.com/video/BV1iM4y1y7oA\">https://www.bilibili.com/video/BV1iM4y1y7oA</a></li>\n<li>秋叶启动器下载：<a href=\"https://pan.quark.cn/s/2c832199b09b\">https://pan.quark.cn/s/2c832199b09b</a></li>\n</ol>","comments":[{"had_liked":false,"id":391599,"user_name":"fireshort","can_delete":false,"product_type":"c3","uid":1008312,"ip_address":"广东","ucode":"10550CA9C6C730","user_header":"https://static001.geekbang.org/account/avatar/00/0f/62/b8/0e1b655e.jpg","comment_is_top":false,"comment_ctime":1718617712,"is_pvip":false,"replies":null,"discussion_count":0,"race_medal":0,"score":2,"product_id":100769401,"comment_content":"现在可能不紧张了？我选到了“A10”啊。","like_count":1}]}