{"id":608147,"title":"38｜避坑指南：判断和循环中的常见错误","content":"<p><strong>课程代码、课件及其他相关资料地址</strong><br>\n<a href=\"https://gitee.com/wilsonyin/zero-basics-python\">https://gitee.com/wilsonyin/zero-basics-python</a></p>","comments":[{"had_liked":false,"id":393050,"user_name":"8000tank","can_delete":false,"product_type":"c3","uid":3838010,"ip_address":"北京","ucode":"C5DC98A0EB57CE","user_header":"","comment_is_top":false,"comment_ctime":1722589778,"is_pvip":false,"replies":[{"id":142771,"content":"同样推荐！ 缩进是新手写Python最容易出错的地方，有自动缩进之后，可以专注写逻辑，之后再完善格式","user_name":"作者回复","user_name_real":"编辑","uid":1056235,"ctime":1723004457,"ip_address":"广东","comment_id":393050,"utype":1}],"discussion_count":1,"race_medal":0,"score":2,"product_id":100310001,"comment_content":"缩进问题，Python Indent是一个适用于VS Code的Python插件，可以自动调整Python代码的缩进，强烈推荐","like_count":1,"discussions":[{"author":{"id":1056235,"avatar":"https://static001.geekbang.org/account/avatar/00/10/1d/eb/b2123759.jpg","nickname":"尹会生","note":"","ucode":"D1093DBD093617","race_medal":0,"user_type":2,"is_pvip":false},"reply_author":{"id":0,"avatar":"","nickname":"","note":"","ucode":"","race_medal":0,"user_type":1,"is_pvip":false},"discussion":{"id":649203,"discussion_content":"同样推荐！ 缩进是新手写Python最容易出错的地方，有自动缩进之后，可以专注写逻辑，之后再完善格式","likes_number":0,"is_delete":false,"is_hidden":false,"ctime":1723004457,"is_liked":false,"can_delete":false,"is_complain":false,"is_top":true,"parent_id":0,"ip_address":"广东","group_id":0},"score":2,"extra":"{\"reply\":true,\"user_type\":2,\"source\":0}","child_discussion_number":0,"child_discussions":[]}]},{"had_liked":false,"id":377200,"user_name":"Geek_Mike","can_delete":false,"product_type":"c3","uid":3196376,"ip_address":"云南","ucode":"CFA942192C3B74","user_header":"https://static001.geekbang.org/account/avatar/00/30/c5/d8/c5509b9c.jpg","comment_is_top":false,"comment_ctime":1688055818,"is_pvip":false,"replies":null,"discussion_count":0,"race_medal":0,"score":2,"product_id":100310001,"comment_content":"list1 = [1,2,3,4]\na = 0\nfor i in range(len(list1)): \n\n    #range(len(list1))相当于range(0,4),在遍历过程中i的值依次是0，1，2，3\n\n    a = list1.pop(i) \n\n    #pop默认从索引-1开始删除元素（最后一个），但如果pop的参数定成i，就是从0开始（第一个）。这样的话，第一个被删掉和返回的值是0号元素1，第二个被删掉和返回的值是1号元素3（这轮循环中列表是[2,3,4]）。当第三次pop尝试删掉2号元素时，发现列表里只剩[2,4]且索引只能到1了。所以报错：pop index out of range\n    \n    print(a) #输出结果：1 3，然后报错pop index out of range。不建议在遍历的过程中更改列表的长度。","like_count":2},{"had_liked":false,"id":366978,"user_name":"yanyu-xin","can_delete":false,"product_type":"c3","uid":1899757,"ip_address":"广东","ucode":"3AA389F9E4C236","user_header":"","comment_is_top":false,"comment_ctime":1674727857,"is_pvip":false,"replies":null,"discussion_count":1,"race_medal":0,"score":2,"product_id":100310001,"comment_content":"按课程举例练习，如下，列表数据是被修改，但程序没有出错的。建议适当修改举例\nlist1 = [ &#39;a&#39;, &#39;b&#39;, &#39;c&#39;, &#39;d&#39; ]\nfor i in range( len( list1 ) ):\n    print(i)\n    list1.pop()\n    print(list1)\n\n&#39;&#39;&#39;0\n[&#39;a&#39;, &#39;b&#39;, &#39;c&#39;]\n1\n[&#39;a&#39;, &#39;b&#39;]\n2\n[&#39;a&#39;]\n3\n[]\n&#39;&#39;&#39;","like_count":0,"discussions":[{"author":{"id":1904632,"avatar":"https://static001.geekbang.org/account/avatar/00/1d/0f/f8/e1b9c1cc.jpg","nickname":"sunny","note":"","ucode":"12350F6FF873D1","race_medal":0,"user_type":1,"is_pvip":false},"reply_author":{"id":0,"avatar":"","nickname":"","note":"","ucode":"","race_medal":0,"user_type":1,"is_pvip":false},"discussion":{"id":601715,"discussion_content":"list1.pop(i)  ,这句话你写错了","likes_number":0,"is_delete":false,"is_hidden":false,"ctime":1675387242,"is_liked":false,"can_delete":false,"is_complain":false,"is_top":false,"parent_id":0,"ip_address":"江苏","group_id":0},"score":2,"extra":"","child_discussion_number":0,"child_discussions":[]}]},{"had_liked":false,"id":365233,"user_name":"江江儿嘛哩哄","can_delete":false,"product_type":"c3","uid":1928117,"ip_address":"浙江","ucode":"E7D6E59551B7F1","user_header":"https://static001.geekbang.org/account/avatar/00/1d/6b/b5/14586a78.jpg","comment_is_top":false,"comment_ctime":1672287732,"is_pvip":false,"replies":null,"discussion_count":0,"race_medal":0,"score":2,"product_id":100310001,"comment_content":"视频中的小练习：\nlist1 = [&#39;a&#39;,&#39;b&#39;,&#39;c&#39;,&#39;d&#39;]\nfor i in range(len(list1)):\n    list1.pop()\n    print(len(list1))","like_count":0}]}